rer.blocks2html-1.0.1-py3.10-nspkg.pth
rer/blocks2html/__init__.py
rer/blocks2html/blocks_converter.py
rer/blocks2html/config.py
rer/blocks2html/configure.zcml
rer/blocks2html/interfaces.py
rer/blocks2html/slate2html.py
rer/blocks2html/testing.py
rer/blocks2html/tests/__init__.py
rer/blocks2html/tests/test_setup.py
rer.blocks2html-1.0.1.dist-info/LICENSE.GPL
rer.blocks2html-1.0.1.dist-info/LICENSE.rst
rer.blocks2html-1.0.1.dist-info/METADATA
rer.blocks2html-1.0.1.dist-info/WHEEL
rer.blocks2html-1.0.1.dist-info/entry_points.txt
rer.blocks2html-1.0.1.dist-info/namespace_packages.txt
rer.blocks2html-1.0.1.dist-info/top_level.txt
rer.blocks2html-1.0.1.dist-info/RECORD
